asciiop/__init__.py
asciiop/asciicvt.py
asciiop-0.1.0.dist-info/METADATA
asciiop-0.1.0.dist-info/WHEEL
asciiop-0.1.0.dist-info/top_level.txt
asciiop-0.1.0.dist-info/RECORD
