Metadata-Version: 2.4
Name: asciiop
Version: 0.1.0
Summary: Operation the ascii
Author-email: 刘浩天 <minecraftcaldson@outlook.com>
Requires-Python: >=3.6
